namakoura/__main__.py
namakoura-0.0.1.dist-info/LICENSE
namakoura-0.0.1.dist-info/METADATA
namakoura-0.0.1.dist-info/WHEEL
namakoura-0.0.1.dist-info/RECORD
